prarthana/__init__.py
prarthana/math_utils.py
prarthana/string_utils.py
prarthana_package-0.1.dist-info/LICENSE
prarthana_package-0.1.dist-info/METADATA
prarthana_package-0.1.dist-info/WHEEL
prarthana_package-0.1.dist-info/top_level.txt
prarthana_package-0.1.dist-info/RECORD
